vell/__init__.py
vell/config.py
vell/spell.py
vell/vell.py
vell-1.0.5.dist-info/LICENSE
vell-1.0.5.dist-info/METADATA
vell-1.0.5.dist-info/WHEEL
vell-1.0.5.dist-info/entry_points.txt
vell-1.0.5.dist-info/top_level.txt
vell-1.0.5.dist-info/RECORD
