Metadata-Version: 2.1
Name: vell
Version: 1.0.5
Summary: Check spell for mutiple files in a project
Home-page: https://github.com/nguyencuong382/vell
Author: nguyencuong382
Author-email: nguyenmanhcuong382@gmail.com
License: MIT
Keywords: check,spell
Platform: UNKNOWN
Classifier: Development Status :: 3 - Alpha
Classifier: Intended Audience :: Developers
Classifier: Topic :: Software Development :: Build Tools
Classifier: License :: OSI Approved :: MIT License
Classifier: Programming Language :: Python :: 3
Classifier: Programming Language :: Python :: 3.4
Classifier: Programming Language :: Python :: 3.5
Classifier: Programming Language :: Python :: 3.6
Requires-Dist: pyspellchecker (==0.4.0)
Requires-Dist: beautifulsoup4 (==4.7.1)
